ntp_amplification.py
ntp_amplification-1.7.2.data/scripts/ntp_amplification.py
ntp_amplification-1.7.2.dist-info/LICENSE
ntp_amplification-1.7.2.dist-info/METADATA
ntp_amplification-1.7.2.dist-info/WHEEL
ntp_amplification-1.7.2.dist-info/entry_points.txt
ntp_amplification-1.7.2.dist-info/top_level.txt
ntp_amplification-1.7.2.dist-info/RECORD
