Metadata-Version: 2.1
Name: ntp-amplification
Version: 1.7.2
Summary: NTP-Amplification Attack Tool
Home-page: https://github.com/cavoq/ntp-amplification
Author: cavoq
Author-email: cavoq@proton.me
License: BSD 2-Clause simplified License
Requires-Python: >=3.9
License-File: LICENSE
Requires-Dist: termcolor==3.1.0
Requires-Dist: pyfiglet==1.0.4
Requires-Dist: scapy==2.6.1
Requires-Dist: pathlib==1.0.1
Requires-Dist: setuptools==74.1.2
